commonhelper/__init__.py
commonhelper-0.0.5.dist-info/METADATA
commonhelper-0.0.5.dist-info/WHEEL
commonhelper-0.0.5.dist-info/top_level.txt
commonhelper-0.0.5.dist-info/RECORD
